LICENSE
MANIFEST.in
README.md
setup.py
zk_grpc/__init__.py
zk_grpc/aio.py
zk_grpc/basic.py
zk_grpc/definition.py
zk_grpc/lbs.py
zk_grpc.egg-info/PKG-INFO
zk_grpc.egg-info/SOURCES.txt
zk_grpc.egg-info/dependency_links.txt
zk_grpc.egg-info/requires.txt
zk_grpc.egg-info/top_level.txt