Metadata-Version: 2.1
Name: zk-grpc
Version: 0.1.0
Summary: a zookeeper registration center manager for python grpcio
Home-page: https://github.com/laiyongtao/zk_grpc
Author: laiyongtao
Author-email: laiyongtao6908@163.com
License: MIT License
Keywords: grpc,zookeeper,kazoo,registration,discovery
Platform: all
Classifier: Programming Language :: Python
Classifier: Programming Language :: Python :: 3
Classifier: Programming Language :: Python :: 3.5
Classifier: Programming Language :: Python :: 3.6
Classifier: Programming Language :: Python :: 3.7
Classifier: Programming Language :: Python :: 3.8
Requires-Python: >3.5.*, <4
